mailapi_freetools/__init__.py
mailapi_freetools/mailapi_freetools.py
mailapi_freetools-0.1.0.dist-info/METADATA
mailapi_freetools-0.1.0.dist-info/WHEEL
mailapi_freetools-0.1.0.dist-info/top_level.txt
mailapi_freetools-0.1.0.dist-info/RECORD
