Metadata-Version: 2.4
Name: mailapi_freetools
Version: 0.1.0
Summary: Lightweight Python SDK for MailAPI (https://mailapi.freetools.fr)
Author: ImAnonFR
License: MIT
Project-URL: Homepage, https://github.com/ImAnonFR/MailAPI-PythonSDK
Project-URL: Repository, https://github.com/ImAnonFR/MailAPI-PythonSDK.git
Keywords: mailapi,temp mail,sdk,email,mailapi freetools
Classifier: Programming Language :: Python :: 3
Classifier: License :: OSI Approved :: MIT License
Classifier: Operating System :: OS Independent
Requires-Python: >=3.8
Requires-Dist: httpx>=0.23
